rtl/first test/cpu_bus.sv
`default_nettype none
module cpu_bus(
    input logic clk_33mhz,
    input logic button_reset,
    input logic ads_n,
    input logic [31:2] a,
    input logic [3:0] be_n,
    input logic m_io,
    input logic d_c,
    input logic w_r,
    input logic req_valid,
    inout wire [31:0] d,
    output wire cpu_clk,
    output logic rdy_n,
    output logic sys_reset,
    output logic [31:0] address_internal,
    output logic [3:0] be_internal,
    output logic add_decode_sel,
    // output logic rom_selected        # leave this to address decoder to choose and select
    input logic response_ready,
    input logic [31:0] response_data_read,
    input logic decode_hit // included here for switching fsm states, as opposed to thought earlier when i didnt need, THIS IS FROM THE ADDRESS DECODER TO TELL US WHETHER OUR ADDRESS REQUEST IS VALID OR NOT

);

logic [31:0] data_out;
logic [3:0] saved_be_n;
logic [31:0] saved_address;
logic data_output_enable;
logic [1:0] divider;

always_ff @(posedge clk_33mhz or posedge button_reset) begin
    if (button_reset)
        divider <= 2'b00;
    else
        divider <= divider + 1'b1;
end
assign cpu_clk = divider[1];

logic [2:0] current_state;
logic [2:0] next_state;
logic [15:0] cycle_count;

localparam RESET_FULL   = 3'b000;
localparam IDLE         = 3'b001;
localparam REQUEST      = 3'b010;
localparam WAIT_RESPONSE = 3'b011;
localparam ACK_AND_RECV = 3'b100;
localparam SEND         = 3'b101;
localparam CLEANUP      = 3'b110;

logic saved_m_io;
logic saved_d_c;
logic saved_w_r;


// cpu_clk is 33 MHz divided by four, or 8.25 MHz (for now)
always_ff @(posedge clk_33mhz or posedge button_reset) begin
    if (button_reset) begin
        cycle_count <= 16'd0;
        sys_reset   <= 1'b1;
    end
    else if (cycle_count < 16'd33_000) begin
        cycle_count <= cycle_count + 1'b1;
        sys_reset   <= 1'b1;
    end
    else begin
        sys_reset <= 1'b0;
    end
end


// after ADS# is sampled cpu is allowed to change address and control signals for later bus activity
// therefore all fields needed for this transaction must be saved here

always_ff @(posedge cpu_clk or posedge button_reset) begin
    if (button_reset) begin
        current_state <= RESET_FULL;

        saved_address <= 32'd0;
        saved_be_n    <= 4'hf;
        saved_m_io    <= 1'b0;
        saved_d_c     <= 1'b0;
        saved_w_r     <= 1'b0;
        data_out      <= 32'd0;
    end
    else begin
        current_state <= next_state;
        // latch the complete bus request when ADS# is asserted
        // a[31:2] does not include the two byte-address bits so append 2'b00 to create a byte address.
        if ((current_state == IDLE) && !ads_n) begin
            saved_address <= {a[31:2], 2'b00};
            saved_be_n    <= be_n;
            saved_m_io    <= m_io;
            saved_d_c     <= d_c;
            saved_w_r     <= w_r;
        end
        // response_data_read is captured before RDY# is asserted, thus the data is stable for the entire SEND state.
        if ((current_state == WAIT_RESPONSE) && response_ready) begin
            data_out      <= response_data_read;
        end
    end
end



// cpu data bus must be driven only during a read response, at all other times this module releases d[31:0]
assign d = data_output_enable ? data_out : 32'hzzzz_zzzz;


// next state and output logic, aka the part that makes the mealy machine a mealy machine 
// defaults describe the inactive bus state:
//   RDY# inactive = 1
//   data bus released
//   no address decoder request
always_comb begin
    next_state = current_state;
    rdy_n              = 1'b1;
    data_output_enable = 1'b0;
    add_decode_sel     = 1'b0;
    address_internal = saved_address;
    be_internal      = saved_be_n;

    case (current_state)
        RESET_FULL: begin
            // sys_reset itself is generated in the clk_33mhz block
            // stay here until that reset interval has finished
            if (!sys_reset)
                next_state = IDLE;
        end


        IDLE: begin
            if (!ads_n) begin

                next_state = REQUEST;
            end
            else begin
                next_state = IDLE;
            end
        end

        REQUEST: begin
            /*
            priority casez (be_n)
                4'b???0: begin encoded = 2'd0; end
                4'b??01: begin encoded = 2'd1; end
                4'b?011: begin encoded = 2'd2; end
                4'b0111: begin encoded = 2'd3; end
                default: begin encoded = 2'd0; end
            endcase

            address_internal[7:0] <= be_n[0] && 1'b1 ? {a[7:2], encoded[1:0]} : 8'd0;
            address_internal[15:8] <= be_n[1] && 1'b1 ? a[15:8] : 8'd0;
            address_internal[23:16] <= be_n[1] && 1'b1 ? a[23:16] : 8'd0;
            address_internal[31:24] <= be_n[1] && 1'b1 ? a[31:24] : 8'd0;
            */
            // and after i went through the trouble of writing all this logic too..... llms are fucking unreliable for asking literally any question even when you hand them the info on a silver fucking platter
            // fuck my chud life

            // keep the request asserted until the address decoder says it has a valid/selected target
            add_decode_sel = 1'b1;
            if (decode_hit)
                next_state = WAIT_RESPONSE;
            else
                next_state = REQUEST;
        end


        WAIT_RESPONSE: begin
            if (response_ready) begin
                next_state = ACK_AND_RECV;
            end
            else begin
                next_state = WAIT_RESPONSE;
            end
        end


        ACK_AND_RECV: begin
            //response data was registered on the clock edge that moved the fsm out of WAIT_RESPONSE
            next_state = SEND;
        end


        SEND: begin
            // RDY# is active low
            // data_out was capture before entering this state so cpu see stable valid data while RDY# low
            rdy_n              = 1'b0;
            if (!saved_w_r) begin
                data_output_enable = 1'b1;
            end
            next_state = CLEANUP;
        end

        CLEANUP: begin
            rdy_n              = 1'b1;
            data_output_enable = 1'b0;
            if (ads_n) begin
                next_state = IDLE;
            end
        end

        default: begin
            next_state = RESET_FULL;
        end

    endcase

end

endmodule

`default_nettype wire

archived/first test/cpu_bus_tb.sv
`timescale 1ns/1ps
`default_nettype none

module cpu_bus_tb;

    logic        clk_33mhz;
    logic        button_reset;

    logic        ads_n;
    logic [31:2] a;
    logic [3:0]  be_n;
    logic        m_io;
    logic        d_c;
    logic        w_r;

    logic        response_ready;
    logic [31:0] response_data_read;
    logic        req_valid;


    wire         cpu_clk;
    wire         rdy_n;
    wire         sys_reset;

    wire [31:0]  address_internal;
    wire [3:0]   be_internal;
    wire         add_decode_sel;


    tri [31:0] d;

    // simulated a0486 cpu can drive this during write transactions. remain disable during first read test.
    logic [31:0] cpu_data_out;
    logic        cpu_data_oe;

    assign d = cpu_data_oe
             ? cpu_data_out
             : 32'hZZZZ_ZZZZ;

    // 33 mhz input clock
    initial begin
        clk_33mhz = 1'b0;

        // approx 33 mhz, full period ≈ 30.303 ns
        forever #15.1515 clk_33mhz = ~clk_33mhz;
    end

    cpu_bus dut (
        .clk_33mhz         (clk_33mhz),
        .button_reset      (button_reset),

        .ads_n             (ads_n),
        .a                 (a),
        .be_n              (be_n),
        .m_io              (m_io),
        .d_c               (d_c),
        .w_r               (w_r),

        .d                 (d),

        .cpu_clk           (cpu_clk),
        .rdy_n             (rdy_n),
        .sys_reset         (sys_reset),

        .address_internal  (address_internal),
        .be_internal       (be_internal),
        .add_decode_sel    (add_decode_sel),

        .response_ready    (response_ready),
        .response_data_read(response_data_read),
        .decode_hit        (req_valid)
    );

    // generate one cpu read transaction
    task automatic cpu_read_request (
        input logic [31:0] address,
        input logic [3:0]  byte_enables_n
    );
        begin
            /*
            // change cpu output on falling edge so they stable before dut sample them on rising edge
             */

            @(negedge cpu_clk);

            a     = address[31:2];
            be_n  = byte_enables_n;

            m_io  = 1'b1;  // memory or io transaction (here memory)
            d_c   = 1'b0;  // data or code/control transaction (here c/c)
            w_r   = 1'b0;  // write/read transaction (here read)

            ads_n = 1'b0;

            // ADS# remain assert for one cpu clock.
            @(negedge cpu_clk);
            ads_n = 1'b1;
        end
    endtask

    // main test
    initial begin
        // safe init cpu bus state
        button_reset       = 1'b1;

        ads_n              = 1'b1;
        a                  = '0;
        be_n               = 4'b1111;

        m_io               = 1'b0;
        d_c                = 1'b0;
        w_r                = 1'b0;

        cpu_data_out       = 32'h0000_0000;
        cpu_data_oe        = 1'b0;

        req_valid          = 1'b0;
        response_ready     = 1'b0;
        response_data_read = 32'h0000_0000;

        // gen waveform
        $dumpfile("cpu_bus.vcd");
        $dumpvars(0, cpu_bus_tb);

        // hold fpga side reset button for small time
        repeat (4) @(posedge clk_33mhz);
        button_reset = 1'b0;

        $display("[%0t] waiting for 486 reset to finish", $time);

        // dut internally wait approx 1 ms.
        wait (sys_reset === 1'b0);

        $display("[%0t] 486 RESET release", $time);

        // give ze fsm enough CPU clock edges to move RESET_FULL -> IDLE
        repeat (2) @(posedge cpu_clk);

        // cpu request the reset vector
        $display("[%0t] cpu request FFFFFFF0.", $time);

        cpu_read_request(
            32'hFFFF_FFF0,
            4'b0000
        );

        // wait for bus controller to present saved request to address decoder
        wait (add_decode_sel === 1'b1);

        $display(
            "[%0t] decoder request: address=%08h BE#=%b",
            $time,
            address_internal,
            be_internal
        );

        // check if cpu request was capture correct
        if (address_internal !== 32'hFFFF_FFF0) begin
            $fatal(
                1,
                "wrong internal address: expected FFFFFFF0, got %08h",
                address_internal
            );
        end

        if (be_internal !== 4'b0000) begin
            $fatal(
                1,
                "wrong byte enables: expected 0000, got %b",
                be_internal
            );
        end

        // simulated address decoder say "yes you have come to correct house"
        @(negedge cpu_clk);
        req_valid = 1'b1;

        @(negedge cpu_clk);
        req_valid = 1'b0;

        // simulate some rom latency because no flash chip move fast like flash. even the flash is limit by speed of light.
        repeat (2) @(posedge cpu_clk);

        // boot rom return four NOP byte for now (will change it to proper program)
        @(negedge cpu_clk);

        response_data_read = 32'h9090_9090;
        response_ready     = 1'b1;

        @(negedge cpu_clk);
        response_ready     = 1'b0;

        /*
        // wait for fpga to assert RDY#
         */
        wait (rdy_n === 1'b0);

        // small delay let combinational outputs settle
        #1;

        $display(
            "[%0t] RDY# asserted, cpu data bus=%08h",
            $time,
            d
        );

        if (d !== 32'h9090_9090) begin
            $fatal(
                1,
                "wrong cpu read data: expected 90909090, got %08h",
                d
            );
        end

        // cpu sample data on this rising edge while RDY# low
        @(posedge cpu_clk);
        #1;

        // wait for cleanup
        wait (rdy_n === 1'b1);
        repeat (2) @(posedge cpu_clk);

        // after the read completes check if fpga release d31-d0
        if (d !== 32'hZZZZ_ZZZZ) begin
            $fatal(
                1,
                "cpu data bus was not released after transaction: %08h",
                d
            );
        end

        $display("");
        $display("pass, reset-vector transaction complete");
        $display("address: FFFFFFF0");
        $display("data:    90909090");
        $display("");

        #100;
        $finish;
    end

    // timeout protection

    initial begin
        // reset timer itself take approx 1 ms
        #2_000_000;

        $fatal(
            1,
            "timeout, fsm failed to complete transaction"
        );
    end

endmodule

`default_nettype wire

rtl/first test/cpu_bus.vcd
$date
	Tue Aug 04 00:26:49 2026
$end
$version
	Icarus Verilog
$end
$timescale
	1ps
$end
$scope module cpu_bus_tb $end
$var wire 32 ! d [31:0] $end
$var wire 1 " sys_reset $end
$var wire 1 # rdy_n $end
$var wire 1 $ cpu_clk $end
$var wire 4 % be_internal [3:0] $end
$var wire 32 & address_internal [31:0] $end
$var wire 1 ' add_decode_sel $end
$var reg 30 ( a [31:2] $end
$var reg 1 ) ads_n $end
$var reg 4 * be_n [3:0] $end
$var reg 1 + button_reset $end
$var reg 1 , clk_33mhz $end
$var reg 1 - cpu_data_oe $end
$var reg 32 . cpu_data_out [31:0] $end
$var reg 1 / d_c $end
$var reg 1 0 m_io $end
$var reg 1 1 req_valid $end
$var reg 32 2 response_data_read [31:0] $end
$var reg 1 3 response_ready $end
$var reg 1 4 w_r $end
$scope module dut $end
$var wire 30 5 a [31:2] $end
$var wire 1 ) ads_n $end
$var wire 4 6 be_n [3:0] $end
$var wire 1 + button_reset $end
$var wire 1 , clk_33mhz $end
$var wire 32 7 d [31:0] $end
$var wire 1 / d_c $end
$var wire 1 1 decode_hit $end
$var wire 1 0 m_io $end
$var wire 1 8 req_valid $end
$var wire 32 9 response_data_read [31:0] $end
$var wire 1 3 response_ready $end
$var wire 1 4 w_r $end
$var wire 1 $ cpu_clk $end
$var parameter 3 : ACK_AND_RECV $end
$var parameter 3 ; CLEANUP $end
$var parameter 3 < IDLE $end
$var parameter 3 = REQUEST $end
$var parameter 3 > RESET_FULL $end
$var parameter 3 ? SEND $end
$var parameter 3 @ WAIT_RESPONSE $end
$var reg 1 ' add_decode_sel $end
$var reg 32 A address_internal [31:0] $end
$var reg 4 B be_internal [3:0] $end
$var reg 3 C current_state [2:0] $end
$var reg 16 D cycle_count [15:0] $end
$var reg 32 E data_out [31:0] $end
$var reg 1 F data_output_enable $end
$var reg 2 G divider [1:0] $end
$var reg 3 H next_state [2:0] $end
$var reg 1 # rdy_n $end
$var reg 32 I saved_address [31:0] $end
$var reg 4 J saved_be_n [3:0] $end
$var reg 1 K saved_d_c $end
$var reg 1 L saved_m_io $end
$var reg 1 M saved_w_r $end
$var reg 1 " sys_reset $end
$upscope $end
$scope task cpu_read_request $end
$upscope $end
$upscope $end
$enddefinitions $end
$comment Show the parameter values. $end
$dumpall
b11 @
b101 ?
b0 >
b10 =
b1 <
b110 ;
b100 :
$end
#0
$dumpvars
0M
0L
0K
b1111 J
b0 I
b0 H
b0 G
0F
b0 E
b0 D
b0 C
b1111 B
b0 A
b0 9
z8
bz 7
b1111 6
b0 5
04
03
b0 2
01
00
0/
b0 .
0-
0,
1+
b1111 *
1)
b0 (
0'
b0 &
b1111 %
0$
1#
1"
bz !
$end
#15152
1,
#30304
0,
#45456
1,
#60608
0,
#75760
1,
#90912
0,
#106064
b1 G
b1 D
0+
1,
#121216
0,
#136368
1$
b10 D
b10 G
1,
#151520
0,
#166672
b11 G
b11 D
1,
#181824
0,
#196976
0$
b100 D
b0 G
1,
#212128
0,
#227280
b1 G
b101 D
1,
#242432
0,
#257584
1$
b110 D
b10 G
1,
#272736
0,
#287888
b11 G
b111 D
1,
#303040
0,
#318192
0$
b1000 D
b0 G
1,
#333344
0,
#348496
b1 G
b1001 D
1,
#363648
0,
#378800
1$
b1010 D
b10 G
1,
#393952
0,
#409104
b11 G
b1011 D
1,
#424256
0,
#439408
0$
b1100 D
b0 G
1,
#454560
0,
#469712
b1 G
b1101 D
1,
#484864
0,
#500016
1$
b1110 D
b10 G
1,
#515168
0,
#530320
b11 G
b1111 D
1,
#545472
0,
#560624
0$
b10000 D
b0 G
1,
#575776
0,
#590928
b1 G
b10001 D
1,
#606080
0,
#621232
1$
b10010 D
b10 G
1,
#636384
0,
#651536
b11 G
b10011 D
1,
#666688
0,
#681840
0$
b10100 D
b0 G
1,
#696992
0,
#712144
b1 G
b10101 D
1,
#727296
0,
#742448
1$
b10110 D
b10 G
1,
#757600
0,
#772752
b11 G
b10111 D
1,
#787904
0,
#803056
0$
b11000 D
b0 G
1,
#818208
0,
#833360
b1 G
b11001 D
1,
#848512
0,
#863664
1$
b11010 D
b10 G
1,
#878816
0,
#893968
b11 G
b11011 D
1,
#909120
0,
#924272
0$
b11100 D
b0 G
1,
#939424
0,
#954576
b1 G
b11101 D
1,
#969728
0,
#984880
1$
b11110 D
b10 G
1,
#1000032
0,
#1015184
b11 G
b11111 D
1,
#1030336
0,
#1045488
0$
b100000 D
b0 G
1,
#1060640
0,
#1075792
b1 G
b100001 D
1,
#1090944
0,
#1106096
1$
b100010 D
b10 G
1,
#1121248
0,
#1136400
b11 G
b100011 D
1,
#1151552
0,
#1166704
0$
b100100 D
b0 G
1,
#1181856
0,
#1197008
b1 G
b100101 D
1,
#1212160
0,
#1227312
1$
b100110 D
b10 G
1,
#1242464
0,
#1257616
b11 G
b100111 D
1,
#1272768
0,
#1287920
0$
b101000 D
b0 G
1,
#1303072
0,
#1318224
b1 G
b101001 D
1,
#1333376
0,
#1348528
1$
b101010 D
b10 G
1,
#1363680
0,
#1378832
b11 G
b101011 D
1,
#1393984
0,
#1409136
0$
b101100 D
b0 G
1,
#1424288
0,
#1439440
b1 G
b101101 D
1,
#1454592
0,
#1469744
1$
b101110 D
b10 G
1,
#1484896
0,
#1500048
b11 G
b101111 D
1,
#1515200
0,
#1530352
0$
b110000 D
b0 G
1,
#1545504
0,
#1560656
b1 G
b110001 D
1,
#1575808
0,
#1590960
1$
b110010 D
b10 G
1,
#1606112
0,
#1621264
b11 G
b110011 D
1,
#1636416
0,
#1651568
0$
b110100 D
b0 G
1,
#1666720
0,
#1681872
b1 G
b110101 D
1,
#1697024
0,
#1712176
1$
b110110 D
b10 G
1,
#1727328
0,
#1742480
b11 G
b110111 D
1,
#1757632
0,
#1772784
0$
b111000 D
b0 G
1,
#1787936
0,
#1803088
b1 G
b111001 D
1,
#1818240
0,
#1833392
1$
b111010 D
b10 G
1,
#1848544
0,
#1863696
b11 G
b111011 D
1,
#1878848
0,
#1894000
0$
b111100 D
b0 G
1,
#1909152
0,
#1924304
b1 G
b111101 D
1,
#1939456
0,
#1954608
1$
b111110 D
b10 G
1,
#1969760
0,
#1984912
b11 G
b111111 D
1,
#2000064
0,
#2015216
0$
b1000000 D
b0 G
1,
#2030368
0,
#2045520
b1 G
b1000001 D
1,
#2060672
0,
#2075824
1$
b1000010 D
b10 G
1,
#2090976
0,
#2106128
b11 G
b1000011 D
1,
#2121280
0,
#2136432
0$
b1000100 D
b0 G
1,
#2151584
0,
#2166736
b1 G
b1000101 D
1,
#2181888
0,
#2197040
1$
b1000110 D
b10 G
1,
#2212192
0,
#2227344
b11 G
b1000111 D
1,
#2242496
0,
#2257648
0$
b1001000 D
b0 G
1,
#2272800
0,
#2287952
b1 G
b1001001 D
1,
#2303104
0,
#2318256
1$
b1001010 D
b10 G
1,
#2333408
0,
#2348560
b11 G
b1001011 D
1,
#2363712
0,
#2378864
0$
b1001100 D
b0 G
1,
#2394016
0,
#2409168
b1 G
b1001101 D
1,
#2424320
0,
#2439472
1$
b1001110 D
b10 G
1,
#2454624
0,
#2469776
b11 G
b1001111 D
1,
#2484928
0,
#2500080
0$
b1010000 D
b0 G
1,
#2515232
0,
#2530384
b1 G
b1010001 D
1,
#2545536
0,
#2560688
1$
b1010010 D
b10 G
1,
#2575840
0,
#2590992
b11 G
b1010011 D
1,
#2606144
0,
#2621296
0$
b1010100 D
b0 G
1,
#2636448
0,
#2651600
b1 G
b1010101 D
1,
#2666752
0,
#2681904
1$
b1010110 D
b10 G
1,
#2697056
0,
#2712208
b11 G
b1010111 D
1,
#2727360
0,
#2742512
0$
b1011000 D
b0 G
1,
#2757664
0,
#2772816
b1 G
b1011001 D
1,
#2787968
0,
#2803120
1$
b1011010 D
b10 G
1,
#2818272
0,
#2833424
b11 G
b1011011 D
1,
#2848576
0,
#2863728
0$
b1011100 D
b0 G
1,
#2878880
0,
#2894032
b1 G
b1011101 D
1,
#2909184
0,
#2924336
1$
b1011110 D
b10 G
1,
#2939488
0,
#2954640
b11 G
b1011111 D
1,
#2969792
0,
#2984944
0$
b1100000 D
b0 G
1,
#3000096
0,
#3015248
b1 G
b1100001 D
1,
#3030400
0,
#3045552
1$
b1100010 D
b10 G
1,
#3060704
0,
#3075856
b11 G
b1100011 D
1,
#3091008
0,
#3106160
0$
b1100100 D
b0 G
1,
#3121312
0,
#3136464
b1 G
b1100101 D
1,
#3151616
0,
#3166768
1$
b1100110 D
b10 G
1,
#3181920
0,
#3197072
b11 G
b1100111 D
1,
#3212224
0,
#3227376
0$
b1101000 D
b0 G
1,
#3242528
0,
#3257680
b1 G
b1101001 D
1,
#3272832
0,
#3287984
1$
b1101010 D
b10 G
1,
#3303136
0,
#3318288
b11 G
b1101011 D
1,
#3333440
0,
#3348592
0$
b1101100 D
b0 G
1,
#3363744
0,
#3378896
b1 G
b1101101 D
1,
#3394048
0,
#3409200
1$
b1101110 D
b10 G
1,
#3424352
0,
#3439504
b11 G
b1101111 D
1,
#3454656
0,
#3469808
0$
b1110000 D
b0 G
1,
#3484960
0,
#3500112
b1 G
b1110001 D
1,
#3515264
0,
#3530416
1$
b1110010 D
b10 G
1,
#3545568
0,
#3560720
b11 G
b1110011 D
1,
#3575872
0,
#3591024
0$
b1110100 D
b0 G
1,
#3606176
0,
#3621328
b1 G
b1110101 D
1,
#3636480
0,
#3651632
1$
b1110110 D
b10 G
1,
#3666784
0,
#3681936
b11 G
b1110111 D
1,
#3697088
0,
#3712240
0$
b1111000 D
b0 G
1,
#3727392
0,
#3742544
b1 G
b1111001 D
1,
#3757696
0,
#3772848
1$
b1111010 D
b10 G
1,
#3788000
0,
#3803152
b11 G
b1111011 D
1,
#3818304
0,
#3833456
0$
b1111100 D
b0 G
1,
#3848608
0,
#3863760
b1 G
b1111101 D
1,
#3878912
0,
#3894064
1$
b1111110 D
b10 G
1,
#3909216
0,
#3924368
b11 G
b1111111 D
1,
#3939520
0,
#3954672
0$
b10000000 D
b0 G
1,
#3969824
0,
#3984976
b1 G
b10000001 D
1,
#4000128
0,
#4015280
1$
b10000010 D
b10 G
1,
#4030432
0,
#4045584
b11 G
b10000011 D
1,
#4060736
0,
#4075888
0$
b10000100 D
b0 G
1,
#4091040
0,
#4106192
b1 G
b10000101 D
1,
#4121344
0,
#4136496
1$
b10000110 D
b10 G
1,
#4151648
0,
#4166800
b11 G
b10000111 D
1,
#4181952
0,
#4197104
0$
b10001000 D
b0 G
1,
#4212256
0,
#4227408
b1 G
b10001001 D
1,
#4242560
0,
#4257712
1$
b10001010 D
b10 G
1,
#4272864
0,
#4288016
b11 G
b10001011 D
1,
#4303168
0,
#4318320
0$
b10001100 D
b0 G
1,
#4333472
0,
#4348624
b1 G
b10001101 D
1,
#4363776
0,
#4378928
1$
b10001110 D
b10 G
1,
#4394080
0,
#4409232
b11 G
b10001111 D
1,
#4424384
0,
#4439536
0$
b10010000 D
b0 G
1,
#4454688
0,
#4469840
b1 G
b10010001 D
1,
#4484992
0,
#4500144
1$
b10010010 D
b10 G
1,
#4515296
0,
#4530448
b11 G
b10010011 D
1,
#4545600
0,
#4560752
0$
b10010100 D
b0 G
1,
#4575904
0,
#4591056
b1 G
b10010101 D
1,
#4606208
0,
#4621360
1$
b10010110 D
b10 G
1,
#4636512
0,
#4651664
b11 G
b10010111 D
1,
#4666816
0,
#4681968
0$
b10011000 D
b0 G
1,
#4697120
0,
#4712272
b1 G
b10011001 D
1,
#4727424
0,
#4742576
1$
b10011010 D
b10 G
1,
#4757728
0,
#4772880
b11 G
b10011011 D
1,
#4788032
0,
#4803184
0$
b10011100 D
b0 G
1,
#4818336
0,
#4833488
b1 G
b10011101 D
1,
#4848640
0,
#4863792
1$
b10011110 D
b10 G
1,
#4878944
0,
#4894096
b11 G
b10011111 D
1,
#4909248
0,
#4924400
0$
b10100000 D
b0 G
1,
#4939552
0,
#4954704
b1 G
b10100001 D
1,
#4969856
0,
#4985008
1$
b10100010 D
b10 G
1,
#5000160
0,
#5015312
b11 G
b10100011 D
1,
#5030464
0,
#5045616
0$
b10100100 D
b0 G
1,
#5060768
0,
#5075920
b1 G
b10100101 D
1,
#5091072
0,
#5106224
1$
b10100110 D
b10 G
1,
#5121376
0,
#5136528
b11 G
b10100111 D
1,
#5151680
0,
#5166832
0$
b10101000 D
b0 G
1,
#5181984
0,
#5197136
b1 G
b10101001 D
1,
#5212288
0,
#5227440
1$
b10101010 D
b10 G
1,
#5242592
0,
#5257744
b11 G
b10101011 D
1,
#5272896
0,
#5288048
0$
b10101100 D
b0 G
1,
#5303200
0,
#5318352
b1 G
b10101101 D
1,
#5333504
0,
#5348656
1$
b10101110 D
b10 G
1,
#5363808
0,
#5378960
b11 G
b10101111 D
1,
#5394112
0,
#5409264
0$
b10110000 D
b0 G
1,
#5424416
0,
#5439568
b1 G
b10110001 D
1,
#5454720
0,
#5469872
1$
b10110010 D
b10 G
1,
#5485024
0,
#5500176
b11 G
b10110011 D
1,
#5515328
0,
#5530480
0$
b10110100 D
b0 G
1,
#5545632
0,
#5560784
b1 G
b10110101 D
1,
#5575936
0,
#5591088
1$
b10110110 D
b10 G
1,
#5606240
0,
#5621392
b11 G
b10110111 D
1,
#5636544
0,
#5651696
0$
b10111000 D
b0 G
1,
#5666848
0,
#5682000
b1 G
b10111001 D
1,
#5697152
0,
#5712304
1$
b10111010 D
b10 G
1,
#5727456
0,
#5742608
b11 G
b10111011 D
1,
#5757760
0,
#5772912
0$
b10111100 D
b0 G
1,
#5788064
0,
#5803216
b1 G
b10111101 D
1,
#5818368
0,
#5833520
1$
b10111110 D
b10 G
1,
#5848672
0,
#5863824
b11 G
b10111111 D
1,
#5878976
0,
#5894128
0$
b11000000 D
b0 G
1,
#5909280
0,
#5924432
b1 G
b11000001 D
1,
#5939584
0,
#5954736
1$
b11000010 D
b10 G
1,
#5969888
0,
#5985040
b11 G
b11000011 D
1,
#6000192
0,
#6015344
0$
b11000100 D
b0 G
1,
#6030496
0,
#6045648
b1 G
b11000101 D
1,
#6060800
0,
#6075952
1$
b11000110 D
b10 G
1,
#6091104
0,
#6106256
b11 G
b11000111 D
1,
#6121408
0,
#6136560
0$
b11001000 D
b0 G
1,
#6151712
0,
#6166864
b1 G
b11001001 D
1,
#6182016
0,
#6197168
1$
b11001010 D
b10 G
1,
#6212320
0,
#6227472
b11 G
b11001011 D
1,
#6242624
0,
#6257776
0$
b11001100 D
b0 G
1,
#6272928
0,
#6288080
b1 G
b11001101 D
1,
#6303232
0,
#6318384
1$
b11001110 D
b10 G
1,
#6333536
0,
#6348688
b11 G
b11001111 D
1,
#6363840
0,
#6378992
0$
b11010000 D
b0 G
1,
#6394144
0,
#6409296
b1 G
b11010001 D
1,
#6424448
0,
#6439600
1$
b11010010 D
b10 G
1,
#6454752
0,
#6469904
b11 G
b11010011 D
1,
#6485056
0,
#6500208
0$
b11010100 D
b0 G
1,
#6515360
0,
#6530512
b1 G
b11010101 D
1,
#6545664
0,
#6560816
1$
b11010110 D
b10 G
1,
#6575968
0,
#6591120
b11 G
b11010111 D
1,
#6606272
0,
#6621424
0$
b11011000 D
b0 G
1,
#6636576
0,
#6651728
b1 G
b11011001 D
1,
#6666880
0,
#6682032
1$
b11011010 D
b10 G
1,
#6697184
0,
#6712336
b11 G
b11011011 D
1,
#6727488
0,
#6742640
0$
b11011100 D
b0 G
1,
#6757792
0,
#6772944
b1 G
b11011101 D
1,
#6788096
0,
#6803248
1$
b11011110 D
b10 G
1,
#6818400
0,
#6833552
b11 G
b11011111 D
1,
#6848704
0,
#6863856
0$
b11100000 D
b0 G
1,
#6879008
0,
#6894160
b1 G
b11100001 D
1,
#6909312
0,
#6924464
1$
b11100010 D
b10 G
1,
#6939616
0,
#6954768
b11 G
b11100011 D
1,
#6969920
0,
#6985072
0$
b11100100 D
b0 G
1,
#7000224
0,
#7015376
b1 G
b11100101 D
1,
#7030528
0,
#7045680
1$
b11100110 D
b10 G
1,
#7060832
0,
#7075984
b11 G
b11100111 D
1,
#7091136
0,
#7106288
0$
b11101000 D
b0 G
1,
#7121440
0,
#7136592
b1 G
b11101001 D
1,
#7151744
0,
#7166896
1$
b11101010 D
b10 G
1,
#7182048
0,
#7197200
b11 G
b11101011 D
1,
#7212352
0,
#7227504
0$
b11101100 D
b0 G
1,
#7242656
0,
#7257808
b1 G
b11101101 D
1,
#7272960
0,
#7288112
1$
b11101110 D
b10 G
1,
#7303264
0,
#7318416
b11 G
b11101111 D
1,
#7333568
0,
#7348720
0$
b11110000 D
b0 G
1,
#7363872
0,
#7379024
b1 G
b11110001 D
1,
#7394176
0,
#7409328
1$
b11110010 D
b10 G
1,
#7424480
0,
#7439632
b11 G
b11110011 D
1,
#7454784
0,
#7469936
0$
b11110100 D
b0 G
1,
#7485088
0,
#7500240
b1 G
b11110101 D
1,
#7515392
0,
#7530544
1$
b11110110 D
b10 G
1,
#7545696
0,
#7560848
b11 G
b11110111 D
1,
#7576000
0,
#7591152
0$
b11111000 D
b0 G
1,
#7606304
0,
#7621456
b1 G
b11111001 D
1,
#7636608
0,
#7651760
1$
b11111010 D
b10 G
1,
#7666912
0,
#7682064
b11 G
b11111011 D
1,
#7697216
0,
#7712368
0$
b11111100 D
b0 G
1,
#7727520
0,
#7742672
b1 G
b11111101 D
1,
#7757824
0,
#7772976
1$
b11111110 D
b10 G
1,
#7788128
0,
#7803280
b11 G
b11111111 D
1,
#7818432
0,
#7833584
0$
b100000000 D
b0 G
1,
#7848736
0,
#7863888
b1 G
b100000001 D
1,
#7879040
0,
#7894192
1$
b100000010 D
b10 G
1,
#7909344
0,
#7924496
b11 G
b100000011 D
1,
#7939648
0,
#7954800
0$
b100000100 D
b0 G
1,
#7969952
0,
#7985104
b1 G
b100000101 D
1,
#8000256
0,
#8015408
1$
b100000110 D
b10 G
1,
#8030560
0,
#8045712
b11 G
b100000111 D
1,
#8060864
0,
#8076016
0$
b100001000 D
b0 G
1,
#8091168
0,
#8106320
b1 G
b100001001 D
1,
#8121472
0,
#8136624
1$
b100001010 D
b10 G
1,
#8151776
0,
#8166928
b11 G
b100001011 D
1,
#8182080
0,
#8197232
0$
b100001100 D
b0 G
1,
#8212384
0,
#8227536
b1 G
b100001101 D
1,
#8242688
0,
#8257840
1$
b100001110 D
b10 G
1,
#8272992
0,
#8288144
b11 G
b100001111 D
1,
#8303296
0,
#8318448
0$
b100010000 D
b0 G
1,
#8333600
0,
#8348752
b1 G
b100010001 D
1,
#8363904
0,
#8379056
1$
b100010010 D
b10 G
1,
#8394208
0,
#8409360
b11 G
b100010011 D
1,
#8424512
0,
#8439664
0$
b100010100 D
b0 G
1,
#8454816
0,
#8469968
b1 G
b100010101 D
1,
#8485120
0,
#8500272
1$
b100010110 D
b10 G
1,
#8515424
0,
#8530576
b11 G
b100010111 D
1,
#8545728
0,
#8560880
0$
b100011000 D
b0 G
1,
#8576032
0,
#8591184
b1 G
b100011001 D
1,
#8606336
0,
#8621488
1$
b100011010 D
b10 G
1,
#8636640
0,
#8651792
b11 G
b100011011 D
1,
#8666944
0,
#8682096
0$
b100011100 D
b0 G
1,
#8697248
0,
#8712400
b1 G
b100011101 D
1,
#8727552
0,
#8742704
1$
b100011110 D
b10 G
1,
#8757856
0,
#8773008
b11 G
b100011111 D
1,
#8788160
0,
#8803312
0$
b100100000 D
b0 G
1,
#8818464
0,
#8833616
b1 G
b100100001 D
1,
#8848768
0,
#8863920
1$
b100100010 D
b10 G
1,
#8879072
0,
#8894224
b11 G
b100100011 D
1,
#8909376
0,
#8924528
0$
b100100100 D
b0 G
1,
#8939680
0,
#8954832
b1 G
b100100101 D
1,
